__init__.py
postcode_parser_uk/__init__.py
postcode_parser_uk/errors.py
postcode_parser_uk/logging.py
postcode_parser_uk/postcode.py
postcode_parser_uk/result.py
postcode_parser_uk/parser/__init__.py
postcode_parser_uk/parser/parser.py
postcode_parser_uk/parser/handlers/__init__.py
postcode_parser_uk/parser/handlers/handler.py
postcode_parser_uk/parser/handlers/onspd_csv_file.py
postcode_parser_uk/parser/handlers/regex.py
postcode_parser_uk/parser/handlers/third_party_api.py
postcode_parser_uk/parser/handlers/types.py
postcode_parser_uk-1.1.1.dist-info/LICENSE
postcode_parser_uk-1.1.1.dist-info/METADATA
postcode_parser_uk-1.1.1.dist-info/WHEEL
postcode_parser_uk-1.1.1.dist-info/top_level.txt
postcode_parser_uk-1.1.1.dist-info/RECORD
