Metadata-Version: 2.1
Name: postcode_parser_uk
Version: 1.1.1
Summary: A Python package to parse UK postcodes
Author-email: Jason Kaufman <jasonkaufman111@gmail.com>
Project-URL: Homepage, https://github.com/JasonKaufman86/postcode-parser-uk
Project-URL: Repository, https://github.com/JasonKaufman86/postcode-parser-uk
Classifier: Programming Language :: Python :: 3
Classifier: License :: OSI Approved :: MIT License
Classifier: Operating System :: OS Independent
Requires-Python: >=3.10
License-File: LICENSE
Requires-Dist: pytest
Requires-Dist: flake8
Requires-Dist: black
Requires-Dist: build
Requires-Dist: python-dotenv
Requires-Dist: pandas
Requires-Dist: requests
Provides-Extra: lint
Requires-Dist: black; extra == "lint"
Requires-Dist: flake8; extra == "lint"
